hdf5_nuclear_data_reader-0.1.0.dist-info/METADATA
hdf5_nuclear_data_reader-0.1.0.dist-info/WHEEL
hdf5_nuclear_data_reader.libs/libaec-dda3378b.so.0
hdf5_nuclear_data_reader.libs/libhdf5-31426894.so.8
hdf5_nuclear_data_reader.libs/libsz-fcfb8163.so.2
hdf5_nuclear_data_reader/__init__.py
hdf5_nuclear_data_reader/hdf5_nuclear_data_reader.cpython-38-x86_64-linux-gnu.so
hdf5_nuclear_data_reader-0.1.0.dist-info/RECORD
