Metadata-Version: 2.4
Name: hdf5_nuclear_data_reader
Version: 0.1.0
Summary: A package for reading nuclear data from HDF5 files in the OpenMC format
Keywords: h5,cross-section,hdf5,openmc,nuclear,data
Home-Page: https://github.com/fusion-energy/hdf5_nuclear_data_reader
Author: Jonathan Shimwell <mail@jshimwell.com>
Author-email: Jonathan Shimwell <mail@jshimwell.com>
License: MIT
Project-URL: Source Code, https://github.com/fusion-energy/hdf5_nuclear_data_reader
